flask_multipass_keycloak.py
flask_multipass_keycloak-0.1.2.dist-info/LICENSE
flask_multipass_keycloak-0.1.2.dist-info/METADATA
flask_multipass_keycloak-0.1.2.dist-info/WHEEL
flask_multipass_keycloak-0.1.2.dist-info/entry_points.txt
flask_multipass_keycloak-0.1.2.dist-info/RECORD
