Metadata-Version: 2.1
Name: Flask-Multipass-Keycloak
Version: 0.1.2
Summary: Flask-Multipass provider for Keycloak
Home-page: https://github.com/unconventionaldotdev/flask-multipass-keycloak
License: MIT
Author: Alejandro Avilés
Author-email: ome@unconventional.dev
Maintainer: Adrian Moennich
Maintainer-email: adrian.moennich@cern.ch
Requires-Python: >=3.9,<4.0
Classifier: Development Status :: 3 - Alpha
Classifier: Environment :: Web Environment
Classifier: Framework :: Flask
Classifier: License :: OSI Approved :: MIT License
Classifier: Programming Language :: Python :: 3
Classifier: Programming Language :: Python :: 3.9
Classifier: Programming Language :: Python :: 3.10
Classifier: Programming Language :: Python :: 3.11
Classifier: Programming Language :: Python :: 3.12
Classifier: Programming Language :: Python :: 3.13
Requires-Dist: flask-multipass[authlib] (>=0.4.3)
Project-URL: Repository, https://github.com/unconventionaldotdev/flask-multipass-keycloak
